lkprf/__init__.py
lkprf/data.py
lkprf/keplerprf.py
lkprf/prfmodel.py
lkprf/tessprf.py
lkprf/utils.py
lkprf/version.py
lkprf-1.1.1.dist-info/METADATA
lkprf-1.1.1.dist-info/WHEEL
lkprf-1.1.1.dist-info/RECORD
