Metadata-Version: 2.1
Name: lkprf
Version: 1.1.1
Summary: 
License: MIT
Author: TESS Science Support Center
Author-email: tesshelp@bigbang.gsfc.nasa.gov>, Christina Hedges <christina.l.hedges@nasa.gov
Requires-Python: >=3.8.1,<4.0
Classifier: License :: OSI Approved :: MIT License
Classifier: Programming Language :: Python :: 3
Classifier: Programming Language :: Python :: 3.9
Classifier: Programming Language :: Python :: 3.10
Classifier: Programming Language :: Python :: 3.11
Classifier: Programming Language :: Python :: 3.12
Requires-Dist: fitsio (>=1.2.4,<2.0.0)
Requires-Dist: numpy (>=1.20.0,<2.0.0)
Requires-Dist: requests (>=2.32.3,<3.0.0)
Requires-Dist: scipy (>=1.8.0)
